plus_pkg/Add.py
plus_pkg/__init__.py
plus_pkg/dd.py
plus_pkg/learning_curve.py
plus_pkg/main.py
plus_pkg/print.py
plus_pkg/sampler.py
plus_pkg/samplerB.py
plus_pkg/icons/number.svg
plus_pkg/icons/plus.svg
plus_pkg/icons/print.svg
plus_pkg-0.0.74.dist-info/LICENSE
plus_pkg-0.0.74.dist-info/METADATA
plus_pkg-0.0.74.dist-info/WHEEL
plus_pkg-0.0.74.dist-info/entry_points.txt
plus_pkg-0.0.74.dist-info/top_level.txt
plus_pkg-0.0.74.dist-info/RECORD
